AUTHORS
LICENSE
MANIFEST.in
README.rst
setup.py
django_medialibrary.egg-info/PKG-INFO
django_medialibrary.egg-info/SOURCES.txt
django_medialibrary.egg-info/dependency_links.txt
django_medialibrary.egg-info/not-zip-safe
django_medialibrary.egg-info/requires.txt
django_medialibrary.egg-info/top_level.txt
medialibrary/__init__.py
medialibrary/admin.py
medialibrary/models.py
medialibrary/serializers.py
medialibrary/urls.py
medialibrary/utils.py
medialibrary/views.py
medialibrary/migrations/0001_initial.py
medialibrary/migrations/0002_auto__add_shelfrelation.py
medialibrary/migrations/0003_auto__add_videothumbnail.py
medialibrary/migrations/0004_auto__add_field_video_duration__add_field_video_height__add_field_vide.py
medialibrary/migrations/0005_auto__add_field_audio_content_type__add_field_video_content_type__add_.py
medialibrary/migrations/0006_auto__chg_field_audio_file__chg_field_video_file__chg_field_image_file.py
medialibrary/migrations/0007_auto__add_field_shelf_meta.py
medialibrary/migrations/__init__.py
medialibrary/tests/__init__.py
medialibrary/tests/models.py
medialibrary/tests/serializers.py
medialibrary/tests/views.py