Metadata-Version: 1.1
Name: django-medialibrary
Version: 1.4.4
Summary: A pluggable django app for media management.
Home-page: https://github.com/pulilab/django-medialibrary
Author: Viktor Nagy
Author-email: v@pulilab.com
License: BSD 3-Clause License, see the LICENSE file for details
Download-URL: https://github.com/pulilab/django-medialibrary/archive/1.1.0.zip
Platform: UNKNOWN
Classifier: Topic :: Internet :: WWW/HTTP :: Dynamic Content
Classifier: Intended Audience :: Developers
Classifier: Programming Language :: Python
Classifier: Programming Language :: Python :: 2.6
Classifier: Programming Language :: Python :: 2.7
Classifier: Framework :: Django
Classifier: Development Status :: 4 - Beta
Classifier: Operating System :: OS Independent
